pymydt/__init__.py
pymydt/modules.py
pymydt-0.1.0.dist-info/METADATA
pymydt-0.1.0.dist-info/WHEEL
pymydt-0.1.0.dist-info/top_level.txt
pymydt-0.1.0.dist-info/RECORD
