Metadata-Version: 2.1
Name: pymydt
Version: 0.1.0
Summary: Python MyDT API
Author: JunHwanKwon
Author-email: gr0442@gmail.com
Requires-Python: >=3.6
